rahulnikamb/__init__.py
rahulnikamb/main.py
rahulnikamb-0.2.dist-info/METADATA
rahulnikamb-0.2.dist-info/WHEEL
rahulnikamb-0.2.dist-info/top_level.txt
rahulnikamb-0.2.dist-info/RECORD
