Metadata-Version: 2.1
Name: rahulnikamb
Version: 0.2
Summary: operation & greeting library
Author-email: codewithrahulnikam@gmail.com
